[
  {
    "NumOfInputContent": 4,
    "TasksList": [
      "daj recenziju preformeru sa id=3"
    ],
    "Id": 1,
    "Name": "marko",
    "Surname": "markovic",
    "Email": "m@gmail.com",
    "Password": "m",
    "Favourites": [],
    "ShowReviews": true,
    "ShowConcact": true,
    "Blocked": false,
    "UserType": "musicEditor",
    "ReviewId": [
      20,
      25,
      26
    ]
  },
  {
    "NumOfInputContent": 1,
    "TasksList": [],
    "Id": 2,
    "Name": "pero",
    "Surname": "peric",
    "Email": "p@gmail.com",
    "Password": "p",
    "Favourites": [],
    "ShowReviews": true,
    "ShowConcact": true,
    "Blocked": false,
    "UserType": "musicEditor",
    "ReviewId": [
      18
    ]
  },
  {
    "NumOfInputContent": 3,
    "TasksList": [],
    "Id": 3,
    "Name": "ana",
    "Surname": "anic",
    "Email": "ana@gmail.com",
    "Password": "ana",
    "Favourites": [],
    "ShowReviews": true,
    "ShowConcact": false,
    "Blocked": false,
    "UserType": "musicEditor",
    "ReviewId": [
      22,
      23,
      24
    ]
  },
  {
    "NumOfInputContent": 0,
    "TasksList": [
      "dodaj album"
    ],
    "Id": 4,
    "Name": "ljilja",
    "Surname": "ljiljic",
    "Email": "ljilja@gmail.com",
    "Password": "ljilja",
    "Favourites": [],
    "ShowReviews": true,
    "ShowConcact": false,
    "Blocked": false,
    "UserType": "musicEditor",
    "ReviewId": []
  },
  {
    "NumOfInputContent": 0,
    "TasksList": [],
    "Id": 5,
    "Name": "petar",
    "Surname": "peric",
    "Email": "perica@gmail.com",
    "Password": "perica",
    "Favourites": [],
    "ShowReviews": true,
    "ShowConcact": true,
    "Blocked": false,
    "UserType": "musicEditor",
    "ReviewId": []
  }
]